so4t_api/__init__.py
so4t_api/so4t_api.py
so4t_api-0.2.1.dist-info/LICENSE
so4t_api-0.2.1.dist-info/METADATA
so4t_api-0.2.1.dist-info/WHEEL
so4t_api-0.2.1.dist-info/top_level.txt
so4t_api-0.2.1.dist-info/RECORD
