Metadata-Version: 2.1
Name: so4t_api
Version: 0.2.1
Summary: An API wrapper for Stack Overflow for Teams
Author-email: Jonathan Klick <jklick@gmail.com>
License: MIT License
Project-URL: Homepage, https://github.com/jklick-so/so4t_api_wrapper
Project-URL: Issues, https://github.com/jklick-so/so4t_api_wrapper/issues
Keywords: Stack Overflow for Teams,Stack Overflow Enterprise,Stack Overflow
Classifier: License :: OSI Approved :: MIT License
Classifier: Development Status :: 4 - Beta
Classifier: Programming Language :: Python
Classifier: Programming Language :: Python :: 3
Classifier: Programming Language :: Python :: 3.8
Classifier: Programming Language :: Python :: 3.9
Classifier: Programming Language :: Python :: 3.10
Classifier: Programming Language :: Python :: 3.11
Classifier: Programming Language :: Python :: 3.12
Classifier: Programming Language :: Python :: 3.13
Classifier: Programming Language :: Python :: 3.14
Classifier: Operating System :: OS Independent
Requires-Python: >=3.8
License-File: LICENSE
Requires-Dist: requests
